vud4.py
vud4-0.0.4.dist-info/METADATA
vud4-0.0.4.dist-info/WHEEL
vud4-0.0.4.dist-info/entry_points.txt
vud4-0.0.4.dist-info/top_level.txt
vud4-0.0.4.dist-info/RECORD
