Metadata-Version: 2.1
Name: vud4
Version: 0.0.4
Summary: comparing effects on mortality between bivalent booster, fully vaccinated and unvaccinated
Home-page: https://github.com/y-takefuji/vud4
Author: yoshiyasu takefuji
Author-email: takefuji@keio.jp
License: UNKNOWN
Project-URL: Bug Tracker, https://github.com/y-takefuji/vud4
Platform: UNKNOWN
Classifier: Programming Language :: Python :: 3
Classifier: License :: OSI Approved :: MIT License
Classifier: Operating System :: OS Independent
Requires-Python: >=3.8
